[
  {
    "transaction_id": "MzQ1NzY2MTI5OGFkaXF6a2N4",
    "barcode": "XDXQ6K8B",
    "type": "CERTNM",
    "date": "2025-03-07",
    "category": "change-of-name",
    "resolutions": [
      {
        "category": "change-of-name",
        "description": "resolution-change-of-name",
        "type": "RES15",
        "subcategory": "resolution",
        "description_values": {
          "resolution_date": "2025-03-06"
        }
      }
    ],
    "associated_filings": [
      {
        "category": "change-of-name",
        "date": "2025-03-07",
        "description": "change-of-name-by-resolution",
        "type": "NM01"
      }
    ],
    "subcategory": "certificate",
    "description": "certificate-change-of-name-company",
    "description_values": {
      "description": "Company name changed tech teh LTD\\certificate issued on 07/03/25"
    },
    "pages": 3,
    "links": {
      "self": "/company/15771089/filing-history/MzQ1NzY2MTI5OGFkaXF6a2N4",
      "document_metadata": "https://document-api.company-information.service.gov.uk/document/mCL86IuJd3hSnelFaat-5RJXkmCSC3pNWOC_xAGoQHE"
    }
  },
  {
    "transaction_id": "MzQyNDQ4ODQwNGFkaXF6a2N4",
    "barcode": "XD4ORYJF",
    "type": "NEWINC",
    "date": "2024-06-11",
    "category": "incorporation",
    "associated_filings": [
      {
        "category": "incorporation",
        "date": "2024-06-11",
        "description": "model-articles-adopted",
        "type": "MODEL ARTICLES"
      },
      {
        "category": "capital",
        "date": "2024-06-11",
        "description": "statement-of-capital",
        "type": "SH01",
        "description_values": {
          "date": "2024-06-11",
          "capital": [
            {
              "currency": "GBP",
              "figure": "1"
            }
          ]
        },
        "action_date": "2024-06-11"
      }
    ],
    "description": "incorporation-company",
    "pages": 11,
    "links": {
      "self": "/company/15771089/filing-history/MzQyNDQ4ODQwNGFkaXF6a2N4",
      "document_metadata": "https://document-api.company-information.service.gov.uk/document/50JWKmC5ph244_vBQhcOU756CX_HbdySsQnwPRh0pes"
    }
  }
]