{
  "company_number": "14550292",
  "company_name": "TECH GEEKSTERS LTD",
  "total_officers": 2,
  "officers": [
    {
      "name": "MALIK ZEDAN, Mehmood",
      "officer_role": "secretary",
      "appointed_on": "2022-12-20",
      "resigned_on": null,
      "nationality": null,
      "country_of_residence": null,
      "occupation": null,
      "address": {
        "address_line_1": "17 King Edwards Road",
        "address_line_2": "Ruislip",
        "country": "United Kingdom",
        "locality": "London",
        "postal_code": "HA4 7AE",
        "premises": "2nd Floor, College House"
      },
      "date_of_birth": {},
      "links": {
        "self": "/company/14550292/appointments/FH1PV4SDNrGTaFLSlvyQ7GwIsrQ",
        "officer": {
          "appointments": "/officers/V_DKL1ktJpwFOYVNVgsq0wOgblg/appointments"
        }
      },
      "former_names": [],
      "identification": {}
    },
    {
      "name": "MALIK ZEDAN, Mehmood",
      "officer_role": "director",
      "appointed_on": "2022-12-20",
      "resigned_on": null,
      "nationality": "Pakistani",
      "country_of_residence": "Pakistan",
      "occupation": "Ceo",
      "address": {
        "address_line_1": "17 King Edwards Road",
        "address_line_2": "Ruislip",
        "country": "United Kingdom",
        "locality": "London",
        "postal_code": "HA4 7AE",
        "premises": "2nd Floor, College House"
      },
      "date_of_birth": {
        "month": 8,
        "year": 1993
      },
      "links": {
        "self": "/company/14550292/appointments/rerYedW1kw8VdxZqRv2cZtamxuA",
        "officer": {
          "appointments": "/officers/vGHmbLoHpC8hFgXA2DrJAp07ZFw/appointments"
        }
      },
      "former_names": [],
      "identification": {}
    }
  ]
}