{
  "company_number": "15431839",
  "company_name": "TECH IR LIMITED",
  "total_officers": 1,
  "officers": [
    {
      "name": "PERIYANNAN, Mahalingam",
      "officer_role": "director",
      "appointed_on": "2024-01-22",
      "resigned_on": null,
      "nationality": "Indian",
      "country_of_residence": "England",
      "occupation": "Company Director",
      "address": {
        "address_line_1": "Lower Addiscombe Road",
        "country": "England",
        "locality": "Croydon",
        "postal_code": "CR0 6RE",
        "premises": "287"
      },
      "date_of_birth": {
        "month": 7,
        "year": 1982
      },
      "links": {
        "self": "/company/15431839/appointments/YkZdkJVipy0Ux06AmAz8sGhCE_k",
        "officer": {
          "appointments": "/officers/IwqyghJdF0IUHZmoB6qo9_4Bp8U/appointments"
        }
      },
      "former_names": [],
      "identification": {}
    }
  ]
}