{
  "company_number": "SC807209",
  "company_name": "TECH ELEVATE LTD",
  "total_officers": 1,
  "officers": [
    {
      "name": "MCNAMARA, Harold",
      "officer_role": "director",
      "appointed_on": "2024-04-16",
      "resigned_on": null,
      "nationality": "British",
      "country_of_residence": "United Kingdom",
      "occupation": "Director",
      "address": {
        "address_line_1": "1 Lochside Avenue",
        "country": "Scotland",
        "locality": "Edinburgh",
        "postal_code": "EH12 9DJ",
        "premises": "Wallace House",
        "region": "Midlothian"
      },
      "date_of_birth": {
        "month": 4,
        "year": 1951
      },
      "links": {
        "self": "/company/SC807209/appointments/HDZY3d9q3WxdJYqTMrUkvNNbFK8",
        "officer": {
          "appointments": "/officers/gdnUABZ_Ce0fXEKPtKGM7zgQfjM/appointments"
        }
      },
      "former_names": [],
      "identification": {}
    }
  ]
}