[
  {
    "address": {
      "address_line_1": "Downsview Drive",
      "country": "England",
      "locality": "Gillingham",
      "postal_code": "SP8 4RL",
      "premises": "26",
      "region": "Dorset"
    },
    "appointed_on": "2023-06-06",
    "is_pre_1992_appointment": false,
    "country_of_residence": "United Kingdom",
    "date_of_birth": {
      "month": 12,
      "year": 1997
    },
    "links": {
      "self": "/company/14918937/appointments/-CbXuI96BM4BTDrRR-Uy25EylBs",
      "officer": {
        "appointments": "/officers/A0RabUfJ8IQRCs2U838ZDWnGKTA/appointments"
      }
    },
    "name": "WARE, David",
    "nationality": "British",
    "occupation": "Computer Consultant",
    "officer_role": "director",
    "person_number": "309856820001"
  },
  {
    "address": {
      "address_line_1": "Newbury",
      "country": "England",
      "locality": "Gillingham",
      "postal_code": "SP8 4QX",
      "premises": "1 Newbury Court"
    },
    "appointed_on": "2023-06-06",
    "is_pre_1992_appointment": false,
    "country_of_residence": "England",
    "date_of_birth": {
      "month": 7,
      "year": 1987
    },
    "links": {
      "self": "/company/14918937/appointments/UTUlRyLLW8d-9rtTRiscNdFsex8",
      "officer": {
        "appointments": "/officers/gfR04oJKmsrtWpEZPcQSTst0uGs/appointments"
      }
    },
    "name": "RYU, Christopher Stuart",
    "nationality": "British",
    "occupation": "Software Engineer",
    "officer_role": "director",
    "resigned_on": "2023-12-23",
    "person_number": "221439100001"
  }
]