[
  {
    "address": {
      "address_line_1": "Stockport Road",
      "country": "England",
      "locality": "Cheadle",
      "postal_code": "SK8 2DP",
      "premises": "143"
    },
    "appointed_on": "2024-12-03",
    "is_pre_1992_appointment": false,
    "country_of_residence": "England",
    "date_of_birth": {
      "month": 3,
      "year": 1996
    },
    "links": {
      "self": "/company/16116748/appointments/2EGHdd3JGTT1Gl8A3kRMmjCxUoM",
      "officer": {
        "appointments": "/officers/NQU00lB73x70DYZXgC3XKStChWA/appointments"
      }
    },
    "name": "ALI, Hasnat",
    "nationality": "Pakistani",
    "occupation": "Self Employed",
    "officer_role": "director",
    "person_number": "313175260001"
  }
]