{
  "company_number": "08075732",
  "company_name": "TECH DESIGN TEAM (UK) LIMITED",
  "company_status": "active",
  "date_of_creation": "2012-05-18",
  "type": "ltd",
  "jurisdiction": "england-wales",
  "sic_codes": [
    "45400"
  ],
  "has_insolvency_history": false,
  "has_charges": false,
  "has_super_secure_pscs": false,
  "can_file": true,
  "registered_office_address": {
    "address_line_1": "Unit 2 Birchwood Way",
    "address_line_2": "Ashwood Business Park",
    "locality": "Ashington",
    "postal_code": "NE63 0XD",
    "region": "Northumberland"
  },
  "annual_return": {},
  "accounts": {
    "accounting_reference_date": {
      "day": "31",
      "month": "12"
    },
    "last_accounts": {
      "made_up_to": "2023-12-31",
      "period_end_on": "2023-12-31",
      "period_start_on": "2023-01-01",
      "type": "total-exemption-full"
    },
    "next_accounts": {
      "due_on": "2025-09-30",
      "overdue": false,
      "period_end_on": "2024-12-31",
      "period_start_on": "2024-01-01"
    },
    "next_due": "2025-09-30",
    "next_made_up_to": "2024-12-31",
    "overdue": false
  },
  "etag": "a9a2c4879dfaafa3958452c029f5adff83e101d1"
}