{
  "company_number": "14975087",
  "company_name": "TECH BA SOLUTIONS LTD",
  "company_status": "active",
  "date_of_creation": "2023-07-03",
  "type": "ltd",
  "jurisdiction": "england-wales",
  "sic_codes": [
    "62020"
  ],
  "has_insolvency_history": false,
  "has_charges": false,
  "has_super_secure_pscs": false,
  "can_file": true,
  "registered_office_address": {
    "address_line_1": "19 Hawkins Lane",
    "country": "England",
    "locality": "Burton-On-Trent",
    "postal_code": "DE14 1PT"
  },
  "annual_return": {},
  "accounts": {
    "accounting_reference_date": {
      "day": "31",
      "month": "07"
    },
    "last_accounts": {
      "made_up_to": "2024-07-31",
      "period_end_on": "2024-07-31",
      "period_start_on": "2023-07-03",
      "type": "unaudited-abridged"
    },
    "next_accounts": {
      "due_on": "2026-04-30",
      "overdue": false,
      "period_end_on": "2025-07-31",
      "period_start_on": "2024-08-01"
    },
    "next_due": "2026-04-30",
    "next_made_up_to": "2025-07-31",
    "overdue": false
  },
  "etag": "699af52f660c35f98a7b7c38e95d4a23481b719d"
}