{
  "company_number": "15066843",
  "company_name": "TECH CHANNEL AMBASSADORS CIC",
  "company_status": "active",
  "date_of_creation": "2023-08-13",
  "type": "private-limited-guarant-nsc",
  "jurisdiction": "england-wales",
  "sic_codes": [
    "85600"
  ],
  "has_insolvency_history": false,
  "has_charges": false,
  "has_super_secure_pscs": false,
  "can_file": true,
  "registered_office_address": {
    "address_line_1": "Towngate House 2-8 Parkstone Road",
    "country": "England",
    "locality": "Poole",
    "postal_code": "BH15 2PW"
  },
  "annual_return": {},
  "accounts": {
    "accounting_reference_date": {
      "day": "31",
      "month": "08"
    },
    "last_accounts": {
      "made_up_to": "2024-08-31",
      "period_end_on": "2024-08-31",
      "period_start_on": "2023-08-13",
      "type": "dormant"
    },
    "next_accounts": {
      "due_on": "2026-05-31",
      "overdue": false,
      "period_end_on": "2025-08-31",
      "period_start_on": "2024-09-01"
    },
    "next_due": "2026-05-31",
    "next_made_up_to": "2025-08-31",
    "overdue": false
  },
  "etag": "0d916173154aa9b57ff6ff503e38948762c7c754"
}