{
  "company_number": "SC779074",
  "company_name": "TECH FIRST IT SOLUTIONS LTD",
  "company_status": "active",
  "date_of_creation": "2023-08-15",
  "type": "ltd",
  "jurisdiction": "scotland",
  "sic_codes": [
    "62020",
    "62090"
  ],
  "has_insolvency_history": false,
  "has_charges": false,
  "has_super_secure_pscs": false,
  "can_file": true,
  "registered_office_address": {
    "address_line_1": "2nd Floor (East) Belgrave Court",
    "address_line_2": "Rosehall Road",
    "country": "Scotland",
    "locality": "Bellshill",
    "postal_code": "ML4 3NR",
    "region": "North Lanarkshire"
  },
  "annual_return": {},
  "accounts": {
    "accounting_reference_date": {
      "day": "31",
      "month": "08"
    },
    "last_accounts": {
      "made_up_to": "2024-08-31",
      "period_end_on": "2024-08-31",
      "period_start_on": "2023-08-15",
      "type": "micro-entity"
    },
    "next_accounts": {
      "due_on": "2026-05-31",
      "overdue": false,
      "period_end_on": "2025-08-31",
      "period_start_on": "2024-09-01"
    },
    "next_due": "2026-05-31",
    "next_made_up_to": "2025-08-31",
    "overdue": false
  },
  "etag": "51460951414fbb874d910c96cf064b856fc2373e"
}