{
  "accounts": {
    "accounting_reference_date": {
      "day": "31",
      "month": "12"
    },
    "last_accounts": {
      "made_up_to": "2023-12-31",
      "period_end_on": "2023-12-31",
      "period_start_on": "2023-01-01",
      "type": "micro-entity"
    },
    "next_accounts": {
      "due_on": "2025-09-30",
      "overdue": false,
      "period_end_on": "2024-12-31",
      "period_start_on": "2024-01-01"
    },
    "next_due": "2025-09-30",
    "next_made_up_to": "2024-12-31",
    "overdue": false
  },
  "can_file": true,
  "company_name": "TECH CONSULTING PARTNERS LTD",
  "company_number": "09032619",
  "company_status": "active",
  "confirmation_statement": {
    "last_made_up_to": "2025-03-24",
    "next_due": "2026-04-07",
    "next_made_up_to": "2026-03-24",
    "overdue": false
  },
  "date_of_creation": "2014-05-09",
  "etag": "bc6557d384640719947147e98b100ce857b51cf4",
  "has_been_liquidated": false,
  "has_charges": false,
  "has_insolvency_history": false,
  "jurisdiction": "england-wales",
  "last_full_members_list_date": "2016-05-09",
  "links": {
    "persons_with_significant_control": "/company/09032619/persons-with-significant-control",
    "self": "/company/09032619",
    "filing_history": "/company/09032619/filing-history",
    "officers": "/company/09032619/officers"
  },
  "registered_office_address": {
    "address_line_1": "18 Brainton Avenue",
    "locality": "Feltham",
    "postal_code": "TW14 0AY",
    "region": "Middlesex"
  },
  "registered_office_is_in_dispute": false,
  "sic_codes": [
    "62020"
  ],
  "type": "ltd",
  "undeliverable_registered_office_address": false,
  "has_super_secure_pscs": false
}