{
  "accounts": {
    "accounting_reference_date": {
      "day": "31",
      "month": "03"
    },
    "last_accounts": {
      "made_up_to": "2024-03-31",
      "period_end_on": "2024-03-31",
      "period_start_on": "2023-04-01",
      "type": "micro-entity"
    },
    "next_accounts": {
      "due_on": "2025-12-31",
      "overdue": false,
      "period_end_on": "2025-03-31",
      "period_start_on": "2024-04-01"
    },
    "next_due": "2025-12-31",
    "next_made_up_to": "2025-03-31",
    "overdue": false
  },
  "can_file": true,
  "company_name": "TECH CRUSH LIMITED",
  "company_number": "10645793",
  "company_status": "active",
  "confirmation_statement": {
    "last_made_up_to": "2025-01-29",
    "next_due": "2026-02-12",
    "next_made_up_to": "2026-01-29",
    "overdue": false
  },
  "date_of_creation": "2017-03-01",
  "etag": "d097faa30aa59abd4f13f51b04ea57e6d4f3e6ee",
  "has_charges": false,
  "has_insolvency_history": false,
  "jurisdiction": "england-wales",
  "links": {
    "persons_with_significant_control": "/company/10645793/persons-with-significant-control",
    "self": "/company/10645793",
    "filing_history": "/company/10645793/filing-history",
    "officers": "/company/10645793/officers"
  },
  "registered_office_address": {
    "address_line_1": "Flat 2 4-5 Market Place",
    "address_line_2": "Bexleyheath",
    "country": "United Kingdom",
    "locality": "Kent",
    "postal_code": "DA6 7DU"
  },
  "registered_office_is_in_dispute": false,
  "sic_codes": [
    "47799",
    "47910"
  ],
  "type": "ltd",
  "undeliverable_registered_office_address": false,
  "has_super_secure_pscs": false
}