{
  "accounts": {
    "accounting_reference_date": {
      "day": "30",
      "month": "09"
    },
    "last_accounts": {
      "made_up_to": "2023-09-30",
      "period_end_on": "2023-09-30",
      "type": "micro-entity"
    }
  },
  "can_file": false,
  "company_name": "TECH HORIIZON LIMITED",
  "company_number": "13626650",
  "company_status": "dissolved",
  "confirmation_statement": {
    "last_made_up_to": "2023-09-15"
  },
  "date_of_cessation": "2024-11-05",
  "date_of_creation": "2021-09-16",
  "etag": "1cd3c616c3a7e2be619be98916a4191da6f10232",
  "has_charges": false,
  "has_insolvency_history": false,
  "jurisdiction": "england-wales",
  "links": {
    "persons_with_significant_control": "/company/13626650/persons-with-significant-control",
    "self": "/company/13626650",
    "filing_history": "/company/13626650/filing-history",
    "officers": "/company/13626650/officers"
  },
  "registered_office_address": {
    "address_line_1": "13626650 - COMPANIES HOUSE DEFAULT ADDRESS",
    "locality": "Cardiff",
    "po_box": "4385",
    "postal_code": "CF14 8LH"
  },
  "registered_office_is_in_dispute": true,
  "sic_codes": [
    "47990"
  ],
  "type": "ltd",
  "undeliverable_registered_office_address": false,
  "has_super_secure_pscs": false
}